statuscake/__init__.py
statuscake/api.py
statuscake/exceptions.py
statuscake-1.4.5.dist-info/LICENSE
statuscake-1.4.5.dist-info/METADATA
statuscake-1.4.5.dist-info/WHEEL
statuscake-1.4.5.dist-info/top_level.txt
statuscake-1.4.5.dist-info/RECORD
