Metadata-Version: 2.1
Name: statuscake
Version: 1.4.5
Summary: API for StatusCake
Home-page: https://github.com/trbs/statuscake/
Author: Trbs
Author-email: trbs@trbs.net
License: ASL
Keywords: statuscake
Platform: UNKNOWN
Classifier: Development Status :: 5 - Production/Stable
Classifier: Intended Audience :: Developers
Classifier: License :: OSI Approved :: Apache Software License
Classifier: Programming Language :: Python :: 2
Classifier: Programming Language :: Python :: 2.7
Classifier: Programming Language :: Python :: 3
Classifier: Programming Language :: Python :: 3.5
Classifier: Programming Language :: Python :: 3.6
Classifier: Programming Language :: Python :: Implementation :: PyPy
Requires-Dist: requests (>=2.20.0)
Requires-Dist: six (>=1.11.0)
